__init__.py
__main__.py
config.py
ip_utils.py
logger.py
api/__init__.py
api/app.py
api/deps.py
api/routes/__init__.py
api/routes/instances.py
api/routes/messages.py
api/routes/traces.py
api/routes/whatsapp.py
channels/__init__.py
channels/base.py
channels/whatsapp/__init__.py
channels/whatsapp/audio_transcriber.py
channels/whatsapp/channel_handler.py
channels/whatsapp/client.py
channels/whatsapp/evolution_api_client.py
channels/whatsapp/evolution_api_sender.py
channels/whatsapp/evolution_client.py
channels/whatsapp/handlers.py
channels/whatsapp/init.py
channels/whatsapp/whatsapp_media_decrypt.py
cli/__init__.py
cli/instance_cli.py
cli/main.py
cli/main_cli.py
cli/telemetry_cli.py
core/__init__.py
core/telemetry.py
db/__init__.py
db/bootstrap.py
db/database.py
db/models.py
db/trace_models.py
services/__init__.py
services/agent_api_client.py
services/agent_service.py
services/automagik_api_client.py
services/discovery_service.py
services/message_router.py
services/trace_service.py
services/user_management_service.py
services/user_service.py
utils/datetime_utils.py
utils/instance_utils.py
utils/payload_tester.py
utils/test_capture.py
automagik_omni-0.2.1.dist-info/METADATA
automagik_omni-0.2.1.dist-info/WHEEL
automagik_omni-0.2.1.dist-info/entry_points.txt
automagik_omni-0.2.1.dist-info/top_level.txt
automagik_omni-0.2.1.dist-info/RECORD
