Metadata-Version: 2.4
Name: automagik-omni
Version: 0.2.1
Summary: Automagik Omni: Multi-tenant omnichannel messaging hub
Author-email: Felipe Rosa <felipe@namastex.ai>, Cezar Vasconcelos <cezar@namastex.ai>
Requires-Python: >=3.12
Requires-Dist: pydantic>=2.10.6
Requires-Dist: pika>=1.3.2
Requires-Dist: python-dotenv>=1.0.1
Requires-Dist: requests>=2.32.3
Requires-Dist: sqlalchemy>=2.0.38
Requires-Dist: psycopg2-binary>=2.9.10
Requires-Dist: boto3>=1.34.0
Requires-Dist: httpx>=0.28.0
Requires-Dist: fastapi>=0.104.0
Requires-Dist: uvicorn>=0.23.2
Requires-Dist: alembic>=1.16.2
Requires-Dist: typer>=0.16.0
Requires-Dist: rich>=14.0.0
Requires-Dist: pytest>=8.0.0
Requires-Dist: pytest-asyncio>=0.21.0
Requires-Dist: pytest-cov>=4.0.0
Requires-Dist: pytz>=2025.2
